preempt/__init__.py
preempt/common.py
preempt/conversation.py
preempt/names_dataset.json
preempt/ner.py
preempt/sanitizer.py
preempt/utils.py
preempt-0.1.27.dist-info/METADATA
preempt-0.1.27.dist-info/WHEEL
preempt-0.1.27.dist-info/RECORD
