Metadata-Version: 2.4
Name: preempt
Version: 0.1.27
Summary: Sanitize prompts containing PII values, while mainting high utility with cryptographic privacy guarantees
Requires-Python: >=3.10
Requires-Dist: names-dataset>=3.3.1
Requires-Dist: names>=0.3.0
Requires-Dist: protobuf>=5.29.4
Requires-Dist: pyfpe>=0.10.3
Requires-Dist: sentencepiece>=0.2.0
Requires-Dist: torch>=2.6.0
Requires-Dist: tqdm>=4.67.1
Requires-Dist: transformers>=4.51.3
